palantir/__init__.py
palantir/cli.py
palantir/config.py
palantir/core.py
palantir/io.py
palantir/plot.py
palantir/plot_utils.py
palantir/preprocess.py
palantir/presults.py
palantir/utils.py
palantir/validation.py
palantir/version.py
palantir-1.4.3.dist-info/licenses/LICENSE
palantir-1.4.3.dist-info/METADATA
palantir-1.4.3.dist-info/WHEEL
palantir-1.4.3.dist-info/entry_points.txt
palantir-1.4.3.dist-info/top_level.txt
palantir-1.4.3.dist-info/RECORD
