Metadata-Version: 2.4
Name: palantir
Version: 1.4.3
Summary: Palantir for modeling continuous cell state and cell fate choices in single cell data
Author-email: Palantir development team <manu.talanki@gmail.com>
License: MIT
Project-URL: Homepage, https://github.com/dpeerlab/palantir
Project-URL: Bug Tracker, https://github.com/dpeerlab/palantir/issues
Classifier: Programming Language :: Python :: 3
Classifier: Programming Language :: Python :: 3.9
Classifier: Programming Language :: Python :: 3.10
Classifier: Programming Language :: Python :: 3.11
Classifier: Programming Language :: Python :: 3.12
Classifier: Programming Language :: Python :: 3.13
Classifier: License :: OSI Approved :: MIT License
Classifier: Operating System :: OS Independent
Classifier: Operating System :: POSIX :: Linux
Classifier: Development Status :: 5 - Production/Stable
Classifier: Topic :: Scientific/Engineering :: Bio-Informatics
Classifier: Topic :: Scientific/Engineering :: Visualization
Requires-Python: >=3.9
License-File: LICENSE
Requires-Dist: numpy>=1.14.2
Requires-Dist: pandas>=0.22.0
Requires-Dist: scipy>=1.3
Requires-Dist: networkx>=2.1
Requires-Dist: scikit-learn
Requires-Dist: joblib
Requires-Dist: matplotlib>=3.8.0
Requires-Dist: anndata>=0.8.0
Requires-Dist: scanpy>=1.6.0
Requires-Dist: mellon>=1.6.1
Requires-Dist: ml_dtypes>=0.5.0
Requires-Dist: igraph>=0.11.8
Provides-Extra: gam
Requires-Dist: pygam; extra == "gam"
Provides-Extra: fcs
Requires-Dist: fcsparser>=0.1.2; extra == "fcs"
Provides-Extra: full
Requires-Dist: pygam; extra == "full"
Requires-Dist: fcsparser>=0.1.2; extra == "full"
Provides-Extra: test-base
Requires-Dist: pytest>=7.0.0; extra == "test-base"
Requires-Dist: pytest-cov>=4.0.0; extra == "test-base"
Requires-Dist: h5py; extra == "test-base"
Provides-Extra: test
Requires-Dist: pytest>=7.0.0; extra == "test"
Requires-Dist: pytest-cov>=4.0.0; extra == "test"
Requires-Dist: h5py; extra == "test"
Requires-Dist: fcsparser>=0.1.2; extra == "test"
Provides-Extra: pre313
Requires-Dist: fcsparser>=0.1.2; extra == "pre313"
Dynamic: license-file
